nutrition_ai/__init__.py
nutrition_ai/advisor/__init__.py
nutrition_ai/advisor/constants.py
nutrition_ai/advisor/conversation.py
nutrition_ai/advisor/tools.py
nutrition_ai/advisor/types.py
nutrition_ai/advisor/vision/__init__.py
nutrition_ai/advisor/vision/tools.py
nutrition_ai/auth.py
nutrition_ai/constants.py
nutrition_ai/fetch.py
nutrition_ai/search.py
nutrition_ai/tools.py
nutrition_ai/types.py
nutrition_ai/vision/__init__.py
nutrition_ai/vision/tools.py
nutrition_ai-0.1.3.dist-info/METADATA
nutrition_ai-0.1.3.dist-info/WHEEL
nutrition_ai-0.1.3.dist-info/RECORD
